AUTHORS.rst
CONTRIBUTING.rst
HISTORY.rst
LICENSE
MANIFEST.in
README.rst
setup.cfg
setup.py
docs/Makefile
docs/authors.rst
docs/conf.py
docs/contributing.rst
docs/history.rst
docs/index.rst
docs/installation.rst
docs/make.bat
docs/readme.rst
docs/usage.rst
docs/images/readme.jpg
talalprotocol/__init__.py
talalprotocol/talalprotocol.py
talalprotocol.egg-info/PKG-INFO
talalprotocol.egg-info/SOURCES.txt
talalprotocol.egg-info/dependency_links.txt
talalprotocol.egg-info/not-zip-safe
talalprotocol.egg-info/requires.txt
talalprotocol.egg-info/top_level.txt
tests/__init__.py
tests/bruteforce_testing.py
tests/customTesting.py
tests/test_talalprotocol.py