Metadata-Version: 1.1
Name: talalprotocol
Version: 0.3.0
Summary: Deep Layered Encryption
Home-page: https://github.com/s3nu/talalprotocol
Author: Team Standy
Author-email: teamstandyy@gmail.com
License: Team Standy License
Keywords: encryption talalprotocol python3
Platform: UNKNOWN
Classifier: Development Status :: 2 - Pre-Alpha
Classifier: Intended Audience :: Developers
Classifier: Natural Language :: English
Classifier: Operating System :: MacOS
Classifier: Programming Language :: Python :: 3
Classifier: Programming Language :: Python :: 3.3
Classifier: Programming Language :: Python :: 3.4
Classifier: Programming Language :: Python :: 3.5
Classifier: Programming Language :: Python :: 3.6
